pyg_rnn/__init__.py
pyg_rnn/rnn_conv.py
pyg_rnn/utils/__init__.py
pyg_rnn/utils/pack.py
pyg_rnnconv-0.1.0.dist-info/licenses/LICENSE
tests/__init__.py
tests/test_1.py
tests/test_rnnconv.py
pyg_rnnconv-0.1.0.dist-info/METADATA
pyg_rnnconv-0.1.0.dist-info/WHEEL
pyg_rnnconv-0.1.0.dist-info/top_level.txt
pyg_rnnconv-0.1.0.dist-info/RECORD
