Metadata-Version: 2.4
Name: pyg-rnnconv
Version: 0.1.0
Summary: RNNConv module for PyTorch Geometric
Home-page: https://github.com/businessabstraction/pyg_rnn
Author: Your Name
Author-email: your.email@example.com
Classifier: Programming Language :: Python :: 3
Classifier: License :: OSI Approved :: MIT License
Classifier: Operating System :: OS Independent
Requires-Python: >=3.8
License-File: LICENSE
Requires-Dist: torch
Requires-Dist: torch-geometric
Requires-Dist: torch-scatter
Dynamic: author
Dynamic: author-email
Dynamic: classifier
Dynamic: description
Dynamic: description-content-type
Dynamic: home-page
Dynamic: license-file
Dynamic: requires-dist
Dynamic: requires-python
Dynamic: summary
